[
    {
        "id": "challenge-01",
        "title": "Healthy Mi",
        "description": "Creative recipes for obesity patients",
        "image": "images/challenges/healthymi.png",
        "url": "https://www.figma.com/proto/b4X9U5Xi7wzE119tGaG3kQ/HealthyMi?page-id=2%3A41&node-id=406-7619&node-type=frame&t=jAIdbphdgaA1qwiP-1&scaling=min-zoom&content-scaling=fixed&starting-point-node-id=406%3A7619",
        "tags": ["hackathon boeringer hingelheim", "3ยบ prize"]
    },
    {
        "id": "challenge-02",
        "title": "Roady",
        "description": "Creative recipes for obesity patients",
        "image": "images/challenges/roady.png",
        "url": "https://www.figma.com/proto/MvV1c8NtkY7E0QCZezK6Hj/Roady?page-id=312%3A4261&node-id=615-325&node-type=frame&viewport=474%2C1352%2C0.22&t=0P49K517hPPfV6wt-1&scaling=min-zoom&content-scaling=fixed&starting-point-node-id=615%3A325",
        "tags": ["hackathon boeringer hingelheim", "app design"]
    },
    {
        "id": "challenge-03",
        "title": "Samsung",
        "description": "Landing page design & layout",
        "image": "images/challenges/samsung.png",
        "url": "https://www.figma.com/proto/SIj30uaBYZgxHaK5nxmDBu/Samsung-challengue?page-id=217%3A210&node-id=217-213&node-type=frame&t=BeDJtLE6X6U6y6zZ-1&scaling=min-zoom&content-scaling=fixed",
        "tags": ["ui design", "html & css"]
    }
]
